{"cik": "0001996810", "entityName": "GE Vernova Inc.", "facts": {"dei": {"EntityCommonStockSharesOutstanding": {"label": "Entity Common Stock, Shares Outstanding", "description": "Indicate number of shares or other units outstanding of each of registrant's classes of capital or common stock or other ownership interests, if and as stated on cover of related periodic report. Where multiple classes or units exist define each class/interest by adding class of stock items such as Common Class A [Member], Common Class B [Member] or Partnership Interest [Member] onto the Instrument [Domain] of the Entity Listings, Instrument.", "units": {"shares": [{"end": "2024-04-26", "val": 274085523, "accn": "0001996810-24-000008", "fy": 2024, "fp": "Q1", "form": "10-Q", "filed": "2024-04-30", "frame": "CY2024Q1I"}, {"end": "2024-07-17", "val": 274802034, "accn": "0001996810-24-000067", "fy": 2024, "fp": "Q2", "form": "10-Q", "filed": "2024-07-24", "frame": "CY2024Q2I"}, {"end": "2024-10-16", "val": 275652970, "accn": "0001996810-24-000083", "fy": 2024, "fp": "Q3", "form": "10-Q", "filed": "2024-10-23", "frame": "CY2024Q3I"}, {"end": "2025-01-15", "val": 275900754, "accn": "0001996810-25-000011", "fy": 2024, "fp": "FY", "form": "10-K", "filed": "2025-02-06", "frame": "CY2024Q4I"}, {"end": "2025-03-31", "val": 272934744, "accn": "0001996810-25-000073", "fy": 2025, "fp": "Q1", "form": "10-Q", "filed": "2025-04-23", "frame": "CY2025Q1I"}, {"end": "2025-06-30", "val": 272223940, "accn": "0001996810-25-000133", "fy": 2025, "fp": "Q2", "form": "10-Q", "filed": "2025-07-23", "frame": "CY2025Q2I"}, {"end": "2025-09-30", "val": 271320459, "accn": "0001996810-25-000160", "fy": 2025, "fp": "Q3", "form": "10-Q", "filed": "2025-10-22", "frame": "CY2025Q3I"}, {"end": "2025-12-31", "val": 269529464, "accn": "0001996810-26-000015", "fy": 2025, "fp": "FY", "form": "10-K", "filed": "2026-01-29", "frame": "CY2025Q4I"}, {"end": "2026-03-31", "val": 268719995, "accn": "0001996810-26-000064", "fy": 2026, "fp": "Q1", "form": "10-Q", "filed": "2026-04-22", "frame": "CY2026Q1I"}]}}}, "us-gaap": {"NetIncomeLoss": {"label": "Net Income (Loss) Attributable to Parent", "description": "The portion of profit or loss for the period, net of income taxes, which is attributable to the parent.", "units": {"USD": [{"start": "2022-01-01", "end": "2022-12-31", "val": -2736000000, "accn": "0001996810-25-000011", "fy": 2024, "fp": "FY", "form": "10-K", "filed": "2025-02-06", "frame": "CY2022"}, {"start": "2023-01-01", "end": "2023-03-31", "val": -315000000, "accn": "0001996810-24-000008", "fy": 2024, "fp": "Q1", "form": "10-Q", "filed": "2024-04-30", "frame": "CY2023Q1"}, {"start": "2023-01-01", "end": "2023-06-30", "val": -465000000, "accn": "0001996810-24-000067", "fy": 2024, "fp": "Q2", "form": "10-Q", "filed": "2024-07-24"}, {"start": "2023-04-01", "end": "2023-06-30", "val": -150000000, "accn": "0001996810-24-000067", "fy": 2024, "fp": "Q2", "form": "10-Q", "filed": "2024-07-24", "frame": "CY2023Q2"}, {"start": "2023-01-01", "end": "2023-09-30", "val": -635000000, "accn": "0001996810-24-000083", "fy": 2024, "fp": "Q3", "form": "10-Q", "filed": "2024-10-23"}, {"start": "2023-07-01", "end": "2023-09-30", "val": -170000000, "accn": "0001996810-24-000083", "fy": 2024, "fp": "Q3", "form": "10-Q", "filed": "2024-10-23", "frame": "CY2023Q3"}, {"start": "2023-01-01", "end": "2023-12-31", "val": -438000000, "accn": "0001996810-25-000011", "fy": 2024, "fp": "FY", "form": "10-K", "filed": "2025-02-06"}, {"start": "2023-01-01", "end": "2023-12-31", "val": -438000000, "accn": "0001996810-26-000015", "fy": 2025, "fp": "FY", "form": "10-K", "filed": "2026-01-29", "frame": "CY2023"}, {"start": "2024-01-01", "end": "2024-03-31", "val": -130000000, "accn": "0001996810-24-000008", "fy": 2024, "fp": "Q1", "form": "10-Q", "filed": "2024-04-30"}, {"start": "2024-01-01", "end": "2024-03-31", "val": -130000000, "accn": "0001996810-25-000073", "fy": 2025, "fp": "Q1", "form": "10-Q", "filed": "2025-04-23", "frame": "CY2024Q1"}, {"start": "2024-01-01", "end": "2024-06-30", "val": 1164000000, "accn": "0001996810-24-000067", "fy": 2024, "fp": "Q2", "form": "10-Q", "filed": "2024-07-24"}, {"start": "2024-01-01", "end": "2024-06-30", "val": 1164000000, "accn": "0001996810-25-000133", "fy": 2025, "fp": "Q2", "form": "10-Q", "filed": "2025-07-23"}, {"start": "2024-04-01", "end": "2024-06-30", "val": 1294000000, "accn": "0001996810-24-000067", "fy": 2024, "fp": "Q2", "form": "10-Q", "filed": "2024-07-24"}, {"start": "2024-04-01", "end": "2024-06-30", "val": 1294000000, "accn": "0001996810-25-000133", "fy": 2025, "fp": "Q2", "form": "10-Q", "filed": "2025-07-23", "frame": "CY2024Q2"}, {"start": "2024-01-01", "end": "2024-09-30", "val": 1068000000, "accn": "0001996810-24-000083", "fy": 2024, "fp": "Q3", "form": "10-Q", "filed": "2024-10-23"}, {"start": "2024-01-01", "end": "2024-09-30", "val": 1068000000, "accn": "0001996810-25-000160", "fy": 2025, "fp": "Q3", "form": "10-Q", "filed": "2025-10-22"}, {"start": "2024-07-01", "end": "2024-09-30", "val": -96000000, "accn": "0001996810-24-000083", "fy": 2024, "fp": "Q3", "form": "10-Q", "filed": "2024-10-23"}, {"start": "2024-07-01", "end": "2024-09-30", "val": -96000000, "accn": "0001996810-25-000160", "fy": 2025, "fp": "Q3", "form": "10-Q", "filed": "2025-10-22", "frame": "CY2024Q3"}, {"start": "2024-01-01", "end": "2024-12-31", "val": 1552000000, "accn": "0001996810-25-000011", "fy": 2024, "fp": "FY", "form": "10-K", "filed": "2025-02-06"}, {"start": "2024-01-01", "end": "2024-12-31", "val": 1552000000, "accn": "0001996810-26-000015", "fy": 2025, "fp": "FY", "form": "10-K", "filed": "2026-01-29", "frame": "CY2024"}, {"start": "2025-01-01", "end": "2025-03-31", "val": 254000000, "accn": "0001996810-25-000073", "fy": 2025, "fp": "Q1", "form": "10-Q", "filed": "2025-04-23"}, {"start": "2025-01-01", "end": "2025-03-31", "val": 254000000, "accn": "0001996810-26-000064", "fy": 2026, "fp": "Q1", "form": "10-Q", "filed": "2026-04-22", "frame": "CY2025Q1"}, {"start": "2025-01-01", "end": "2025-06-30", "val": 768000000, "accn": "0001996810-25-000133", "fy": 2025, "fp": "Q2", "form": "10-Q", "filed": "2025-07-23"}, {"start": "2025-04-01", "end": "2025-06-30", "val": 514000000, "accn": "0001996810-25-000133", "fy": 2025, "fp": "Q2", "form": "10-Q", "filed": "2025-07-23", "frame": "CY2025Q2"}, {"start": "2025-01-01", "end": "2025-09-30", "val": 1220000000, "accn": "0001996810-25-000160", "fy": 2025, "fp": "Q3", "form": "10-Q", "filed": "2025-10-22"}, {"start": "2025-07-01", "end": "2025-09-30", "val": 452000000, "accn": "0001996810-25-000160", "fy": 2025, "fp": "Q3", "form": "10-Q", "filed": "2025-10-22", "frame": "CY2025Q3"}, {"start": "2025-01-01", "end": "2025-12-31", "val": 4884000000, "accn": "0001996810-26-000015", "fy": 2025, "fp": "FY", "form": "10-K", "filed": "2026-01-29", "frame": "CY2025"}, {"start": "2026-01-01", "end": "2026-03-31", "val": 4745000000, "accn": "0001996810-26-000064", "fy": 2026, "fp": "Q1", "form": "10-Q", "filed": "2026-04-22", "frame": "CY2026Q1"}]}}, "RevenueFromContractWithCustomerExcludingAssessedTax": {"label": "Revenue from Contract with Customer, Excluding Assessed Tax", "description": "Amount, excluding tax collected from customer, of revenue from satisfaction of performance obligation by transferring promised good or service to customer. Tax collected from customer is tax assessed by governmental authority that is both imposed on and concurrent with specific revenue-producing transaction, including, but not limited to, sales, use, value added and excise.", "units": {"USD": [{"start": "2022-01-01", "end": "2022-12-31", "val": 29654000000, "accn": "0001996810-25-000011", "fy": 2024, "fp": "FY", "form": "10-K", "filed": "2025-02-06", "frame": "CY2022"}, {"start": "2023-01-01", "end": "2023-03-31", "val": 6822000000, "accn": "0001996810-24-000008", "fy": 2024, "fp": "Q1", "form": "10-Q", "filed": "2024-04-30", "frame": "CY2023Q1"}, {"start": "2023-01-01", "end": "2023-06-30", "val": 14941000000, "accn": "0001996810-24-000067", "fy": 2024, "fp": "Q2", "form": "10-Q", "filed": "2024-07-24"}, {"start": "2023-04-01", "end": "2023-06-30", "val": 8119000000, "accn": "0001996810-24-000067", "fy": 2024, "fp": "Q2", "form": "10-Q", "filed": "2024-07-24", "frame": "CY2023Q2"}, {"start": "2023-01-01", "end": "2023-09-30", "val": 23194000000, "accn": "0001996810-24-000083", "fy": 2024, "fp": "Q3", "form": "10-Q", "filed": "2024-10-23"}, {"start": "2023-07-01", "end": "2023-09-30", "val": 8253000000, "accn": "0001996810-24-000083", "fy": 2024, "fp": "Q3", "form": "10-Q", "filed": "2024-10-23", "frame": "CY2023Q3"}, {"start": "2023-01-01", "end": "2023-12-31", "val": 33239000000, "accn": "0001996810-25-000011", "fy": 2024, "fp": "FY", "form": "10-K", "filed": "2025-02-06"}, {"start": "2023-01-01", "end": "2023-12-31", "val": 33239000000, "accn": "0001996810-26-000015", "fy": 2025, "fp": "FY", "form": "10-K", "filed": "2026-01-29", "frame": "CY2023"}, {"start": "2024-01-01", "end": "2024-03-31", "val": 7260000000, "accn": "0001996810-24-000008", "fy": 2024, "fp": "Q1", "form": "10-Q", "filed": "2024-04-30"}, {"start": "2024-01-01", "end": "2024-03-31", "val": 7260000000, "accn": "0001996810-25-000073", "fy": 2025, "fp": "Q1", "form": "10-Q", "filed": "2025-04-23", "frame": "CY2024Q1"}, {"start": "2024-01-01", "end": "2024-06-30", "val": 15463000000, "accn": "0001996810-24-000067", "fy": 2024, "fp": "Q2", "form": "10-Q", "filed": "2024-07-24"}, {"start": "2024-01-01", "end": "2024-06-30", "val": 15463000000, "accn": "0001996810-25-000133", "fy": 2025, "fp": "Q2", "form": "10-Q", "filed": "2025-07-23"}, {"start": "2024-04-01", "end": "2024-06-30", "val": 8204000000, "accn": "0001996810-24-000067", "fy": 2024, "fp": "Q2", "form": "10-Q", "filed": "2024-07-24"}, {"start": "2024-04-01", "end": "2024-06-30", "val": 8204000000, "accn": "0001996810-25-000133", "fy": 2025, "fp": "Q2", "form": "10-Q", "filed": "2025-07-23", "frame": "CY2024Q2"}, {"start": "2024-01-01", "end": "2024-09-30", "val": 24376000000, "accn": "0001996810-24-000083", "fy": 2024, "fp": "Q3", "form": "10-Q", "filed": "2024-10-23"}, {"start": "2024-01-01", "end": "2024-09-30", "val": 24376000000, "accn": "0001996810-25-000160", "fy": 2025, "fp": "Q3", "form": "10-Q", "filed": "2025-10-22"}, {"start": "2024-07-01", "end": "2024-09-30", "val": 8913000000, "accn": "0001996810-24-000083", "fy": 2024, "fp": "Q3", "form": "10-Q", "filed": "2024-10-23"}, {"start": "2024-07-01", "end": "2024-09-30", "val": 8913000000, "accn": "0001996810-25-000160", "fy": 2025, "fp": "Q3", "form": "10-Q", "filed": "2025-10-22", "frame": "CY2024Q3"}, {"start": "2024-01-01", "end": "2024-12-31", "val": 34935000000, "accn": "0001996810-25-000011", "fy": 2024, "fp": "FY", "form": "10-K", "filed": "2025-02-06"}, {"start": "2024-01-01", "end": "2024-12-31", "val": 34935000000, "accn": "0001996810-26-000015", "fy": 2025, "fp": "FY", "form": "10-K", "filed": "2026-01-29", "frame": "CY2024"}, {"start": "2025-01-01", "end": "2025-03-31", "val": 8032000000, "accn": "0001996810-25-000073", "fy": 2025, "fp": "Q1", "form": "10-Q", "filed": "2025-04-23"}, {"start": "2025-01-01", "end": "2025-03-31", "val": 8032000000, "accn": "0001996810-26-000064", "fy": 2026, "fp": "Q1", "form": "10-Q", "filed": "2026-04-22", "frame": "CY2025Q1"}, {"start": "2025-01-01", "end": "2025-06-30", "val": 17143000000, "accn": "0001996810-25-000133", "fy": 2025, "fp": "Q2", "form": "10-Q", "filed": "2025-07-23"}, {"start": "2025-04-01", "end": "2025-06-30", "val": 9111000000, "accn": "0001996810-25-000133", "fy": 2025, "fp": "Q2", "form": "10-Q", "filed": "2025-07-23", "frame": "CY2025Q2"}, {"start": "2025-01-01", "end": "2025-09-30", "val": 27112000000, "accn": "0001996810-25-000160", "fy": 2025, "fp": "Q3", "form": "10-Q", "filed": "2025-10-22"}, {"start": "2025-07-01", "end": "2025-09-30", "val": 9969000000, "accn": "0001996810-25-000160", "fy": 2025, "fp": "Q3", "form": "10-Q", "filed": "2025-10-22", "frame": "CY2025Q3"}, {"start": "2025-01-01", "end": "2025-12-31", "val": 38068000000, "accn": "0001996810-26-000015", "fy": 2025, "fp": "FY", "form": "10-K", "filed": "2026-01-29", "frame": "CY2025"}, {"start": "2026-01-01", "end": "2026-03-31", "val": 9339000000, "accn": "0001996810-26-000064", "fy": 2026, "fp": "Q1", "form": "10-Q", "filed": "2026-04-22", "frame": "CY2026Q1"}]}}, "StockholdersEquity": {"label": "Stockholders' Equity Attributable to Parent", "description": "Total of all stockholders' equity (deficit) items, net of receivables from officers, directors, owners, and affiliates of the entity which are attributable to the parent. The amount of the economic entity's stockholders' equity attributable to the parent excludes the amount of stockholders' equity which is allocable to that ownership interest in subsidiary equity which is not attributable to the parent (noncontrolling interest, minority interest). This excludes temporary equity and is sometimes called permanent equity.", "units": {"USD": [{"end": "2023-12-31", "val": 7416000000, "accn": "0001996810-24-000008", "fy": 2024, "fp": "Q1", "form": "10-Q", "filed": "2024-04-30"}, {"end": "2023-12-31", "val": 7416000000, "accn": "0001996810-24-000067", "fy": 2024, "fp": "Q2", "form": "10-Q", "filed": "2024-07-24"}, {"end": "2023-12-31", "val": 7416000000, "accn": "0001996810-24-000083", "fy": 2024, "fp": "Q3", "form": "10-Q", "filed": "2024-10-23"}, {"end": "2023-12-31", "val": 7416000000, "accn": "0001996810-25-000011", "fy": 2024, "fp": "FY", "form": "10-K", "filed": "2025-02-06", "frame": "CY2023Q4I"}, {"end": "2024-03-31", "val": 8974000000, "accn": "0001996810-24-000008", "fy": 2024, "fp": "Q1", "form": "10-Q", "filed": "2024-04-30", "frame": "CY2024Q1I"}, {"end": "2024-06-30", "val": 9067000000, "accn": "0001996810-24-000067", "fy": 2024, "fp": "Q2", "form": "10-Q", "filed": "2024-07-24", "frame": "CY2024Q2I"}, {"end": "2024-09-30", "val": 9504000000, "accn": "0001996810-24-000083", "fy": 2024, "fp": "Q3", "form": "10-Q", "filed": "2024-10-23", "frame": "CY2024Q3I"}, {"end": "2024-12-31", "val": 9546000000, "accn": "0001996810-25-000011", "fy": 2024, "fp": "FY", "form": "10-K", "filed": "2025-02-06"}, {"end": "2024-12-31", "val": 9546000000, "accn": "0001996810-25-000073", "fy": 2025, "fp": "Q1", "form": "10-Q", "filed": "2025-04-23"}, {"end": "2024-12-31", "val": 9546000000, "accn": "0001996810-25-000133", "fy": 2025, "fp": "Q2", "form": "10-Q", "filed": "2025-07-23"}, {"end": "2024-12-31", "val": 9546000000, "accn": "0001996810-25-000160", "fy": 2025, "fp": "Q3", "form": "10-Q", "filed": "2025-10-22"}, {"end": "2024-12-31", "val": 9546000000, "accn": "0001996810-26-000015", "fy": 2025, "fp": "FY", "form": "10-K", "filed": "2026-01-29", "frame": "CY2024Q4I"}, {"end": "2025-03-31", "val": 8607000000, "accn": "0001996810-25-000073", "fy": 2025, "fp": "Q1", "form": "10-Q", "filed": "2025-04-23", "frame": "CY2025Q1I"}, {"end": "2025-06-30", "val": 8877000000, "accn": "0001996810-25-000133", "fy": 2025, "fp": "Q2", "form": "10-Q", "filed": "2025-07-23", "frame": "CY2025Q2I"}, {"end": "2025-09-30", "val": 8646000000, "accn": "0001996810-25-000160", "fy": 2025, "fp": "Q3", "form": "10-Q", "filed": "2025-10-22", "frame": "CY2025Q3I"}, {"end": "2025-12-31", "val": 11178000000, "accn": "0001996810-26-000015", "fy": 2025, "fp": "FY", "form": "10-K", "filed": "2026-01-29"}, {"end": "2025-12-31", "val": 11178000000, "accn": "0001996810-26-000064", "fy": 2026, "fp": "Q1", "form": "10-Q", "filed": "2026-04-22", "frame": "CY2025Q4I"}, {"end": "2026-03-31", "val": 13922000000, "accn": "0001996810-26-000064", "fy": 2026, "fp": "Q1", "form": "10-Q", "filed": "2026-04-22", "frame": "CY2026Q1I"}]}}, "StockholdersEquityIncludingPortionAttributableToNoncontrollingInterest": {"label": "Stockholders' Equity, Including Portion Attributable to Noncontrolling Interest", "description": "Amount of stockholders' equity (deficit), net of receivables from officers, directors, owners, and affiliates of the entity, attributable to both the parent and noncontrolling interests. Amount excludes temporary equity. Alternate caption for the concept is permanent equity.", "units": {"USD": [{"end": "2021-12-31", "val": 13729000000, "accn": "0001996810-25-000011", "fy": 2024, "fp": "FY", "form": "10-K", "filed": "2025-02-06", "frame": "CY2021Q4I"}, {"end": "2022-12-31", "val": 11607000000, "accn": "0001996810-24-000008", "fy": 2024, "fp": "Q1", "form": "10-Q", "filed": "2024-04-30"}, {"end": "2022-12-31", "val": 11607000000, "accn": "0001996810-24-000067", "fy": 2024, "fp": "Q2", "form": "10-Q", "filed": "2024-07-24"}, {"end": "2022-12-31", "val": 11607000000, "accn": "0001996810-24-000083", "fy": 2024, "fp": "Q3", "form": "10-Q", "filed": "2024-10-23"}, {"end": "2022-12-31", "val": 11607000000, "accn": "0001996810-25-000011", "fy": 2024, "fp": "FY", "form": "10-K", "filed": "2025-02-06"}, {"end": "2022-12-31", "val": 11607000000, "accn": "0001996810-26-000015", "fy": 2025, "fp": "FY", "form": "10-K", "filed": "2026-01-29", "frame": "CY2022Q4I"}, {"end": "2023-03-31", "val": 10412000000, "accn": "0001996810-24-000008", "fy": 2024, "fp": "Q1", "form": "10-Q", "filed": "2024-04-30"}, {"end": "2023-03-31", "val": 10412000000, "accn": "0001996810-24-000067", "fy": 2024, "fp": "Q2", "form": "10-Q", "filed": "2024-07-24", "frame": "CY2023Q1I"}, {"end": "2023-06-30", "val": 10802000000, "accn": "0001996810-24-000067", "fy": 2024, "fp": "Q2", "form": "10-Q", "filed": "2024-07-24"}, {"end": "2023-06-30", "val": 10802000000, "accn": "0001996810-24-000083", "fy": 2024, "fp": "Q3", "form": "10-Q", "filed": "2024-10-23", "frame": "CY2023Q2I"}, {"end": "2023-09-30", "val": 10454000000, "accn": "0001996810-24-000083", "fy": 2024, "fp": "Q3", "form": "10-Q", "filed": "2024-10-23", "frame": "CY2023Q3I"}, {"end": "2023-12-31", "val": 8380000000, "accn": "0001996810-24-000008", "fy": 2024, "fp": "Q1", "form": "10-Q", "filed": "2024-04-30"}, {"end": "2023-12-31", "val": 8380000000, "accn": "0001996810-24-000067", "fy": 2024, "fp": "Q2", "form": "10-Q", "filed": "2024-07-24"}, {"end": "2023-12-31", "val": 8380000000, "accn": "0001996810-24-000083", "fy": 2024, "fp": "Q3", "form": "10-Q", "filed": "2024-10-23"}, {"end": "2023-12-31", "val": 8380000000, "accn": "0001996810-25-000011", "fy": 2024, "fp": "FY", "form": "10-K", "filed": "2025-02-06"}, {"end": "2023-12-31", "val": 8380000000, "accn": "0001996810-25-000073", "fy": 2025, "fp": "Q1", "form": "10-Q", "filed": "2025-04-23"}, {"end": "2023-12-31", "val": 8380000000, "accn": "0001996810-25-000133", "fy": 2025, "fp": "Q2", "form": "10-Q", "filed": "2025-07-23"}, {"end": "2023-12-31", "val": 8380000000, "accn": "0001996810-25-000160", "fy": 2025, "fp": "Q3", "form": "10-Q", "filed": "2025-10-22"}, {"end": "2023-12-31", "val": 8380000000, "accn": "0001996810-26-000015", "fy": 2025, "fp": "FY", "form": "10-K", "filed": "2026-01-29", "frame": "CY2023Q4I"}, {"end": "2024-03-31", "val": 9980000000, "accn": "0001996810-24-000008", "fy": 2024, "fp": "Q1", "form": "10-Q", "filed": "2024-04-30"}, {"end": "2024-03-31", "val": 9980000000, "accn": "0001996810-24-000067", "fy": 2024, "fp": "Q2", "form": "10-Q", "filed": "2024-07-24"}, {"end": "2024-03-31", "val": 9980000000, "accn": "0001996810-25-000073", "fy": 2025, "fp": "Q1", "form": "10-Q", "filed": "2025-04-23"}, {"end": "2024-03-31", "val": 9980000000, "accn": "0001996810-25-000133", "fy": 2025, "fp": "Q2", "form": "10-Q", "filed": "2025-07-23", "frame": "CY2024Q1I"}, {"end": "2024-06-30", "val": 10049000000, "accn": "0001996810-24-000067", "fy": 2024, "fp": "Q2", "form": "10-Q", "filed": "2024-07-24"}, {"end": "2024-06-30", "val": 10049000000, "accn": "0001996810-24-000083", "fy": 2024, "fp": "Q3", "form": "10-Q", "filed": "2024-10-23"}, {"end": "2024-06-30", "val": 10049000000, "accn": "0001996810-25-000133", "fy": 2025, "fp": "Q2", "form": "10-Q", "filed": "2025-07-23"}, {"end": "2024-06-30", "val": 10049000000, "accn": "0001996810-25-000160", "fy": 2025, "fp": "Q3", "form": "10-Q", "filed": "2025-10-22", "frame": "CY2024Q2I"}, {"end": "2024-09-30", "val": 10517000000, "accn": "0001996810-24-000083", "fy": 2024, "fp": "Q3", "form": "10-Q", "filed": "2024-10-23"}, {"end": "2024-09-30", "val": 10517000000, "accn": "0001996810-25-000160", "fy": 2025, "fp": "Q3", "form": "10-Q", "filed": "2025-10-22", "frame": "CY2024Q3I"}, {"end": "2024-12-31", "val": 10593000000, "accn": "0001996810-25-000011", "fy": 2024, "fp": "FY", "form": "10-K", "filed": "2025-02-06"}, {"end": "2024-12-31", "val": 10593000000, "accn": "0001996810-25-000073", "fy": 2025, "fp": "Q1", "form": "10-Q", "filed": "2025-04-23"}, {"end": "2024-12-31", "val": 10593000000, "accn": "0001996810-25-000133", "fy": 2025, "fp": "Q2", "form": "10-Q", "filed": "2025-07-23"}, {"end": "2024-12-31", "val": 10593000000, "accn": "0001996810-25-000160", "fy": 2025, "fp": "Q3", "form": "10-Q", "filed": "2025-10-22"}, {"end": "2024-12-31", "val": 10593000000, "accn": "0001996810-26-000015", "fy": 2025, "fp": "FY", "form": "10-K", "filed": "2026-01-29"}, {"end": "2024-12-31", "val": 10593000000, "accn": "0001996810-26-000064", "fy": 2026, "fp": "Q1", "form": "10-Q", "filed": "2026-04-22", "frame": "CY2024Q4I"}, {"end": "2025-03-31", "val": 9672000000, "accn": "0001996810-25-000073", "fy": 2025, "fp": "Q1", "form": "10-Q", "filed": "2025-04-23"}, {"end": "2025-03-31", "val": 9672000000, "accn": "0001996810-25-000133", "fy": 2025, "fp": "Q2", "form": "10-Q", "filed": "2025-07-23"}, {"end": "2025-03-31", "val": 9672000000, "accn": "0001996810-26-000064", "fy": 2026, "fp": "Q1", "form": "10-Q", "filed": "2026-04-22", "frame": "CY2025Q1I"}, {"end": "2025-06-30", "val": 9947000000, "accn": "0001996810-25-000133", "fy": 2025, "fp": "Q2", "form": "10-Q", "filed": "2025-07-23"}, {"end": "2025-06-30", "val": 9947000000, "accn": "0001996810-25-000160", "fy": 2025, "fp": "Q3", "form": "10-Q", "filed": "2025-10-22", "frame": "CY2025Q2I"}, {"end": "2025-09-30", "val": 9729000000, "accn": "0001996810-25-000160", "fy": 2025, "fp": "Q3", "form": "10-Q", "filed": "2025-10-22", "frame": "CY2025Q3I"}, {"end": "2025-12-31", "val": 12296000000, "accn": "0001996810-26-000015", "fy": 2025, "fp": "FY", "form": "10-K", "filed": "2026-01-29"}, {"end": "2025-12-31", "val": 12296000000, "accn": "0001996810-26-000064", "fy": 2026, "fp": "Q1", "form": "10-Q", "filed": "2026-04-22", "frame": "CY2025Q4I"}, {"end": "2026-03-31", "val": 15065000000, "accn": "0001996810-26-000064", "fy": 2026, "fp": "Q1", "form": "10-Q", "filed": "2026-04-22", "frame": "CY2026Q1I"}]}}, "CommonStockSharesOutstanding": {"label": "Common Stock, Shares, Outstanding", "description": "Number of shares of common stock outstanding. Common stock represent the ownership interest in a corporation.", "units": {"shares": [{"end": "2024-04-02", "val": 274085523, "accn": "0001996810-24-000067", "fy": 2024, "fp": "Q2", "form": "10-Q", "filed": "2024-07-24"}, {"end": "2024-04-02", "val": 274085523, "accn": "0001996810-24-000083", "fy": 2024, "fp": "Q3", "form": "10-Q", "filed": "2024-10-23"}, {"end": "2024-04-02", "val": 274085523, "accn": "0001996810-25-000011", "fy": 2024, "fp": "FY", "form": "10-K", "filed": "2025-02-06"}, {"end": "2024-04-02", "val": 274085523, "accn": "0001996810-25-000073", "fy": 2025, "fp": "Q1", "form": "10-Q", "filed": "2025-04-23"}, {"end": "2024-04-02", "val": 274085523, "accn": "0001996810-25-000133", "fy": 2025, "fp": "Q2", "form": "10-Q", "filed": "2025-07-23"}, {"end": "2024-04-02", "val": 274085523, "accn": "0001996810-25-000160", "fy": 2025, "fp": "Q3", "form": "10-Q", "filed": "2025-10-22"}, {"end": "2024-04-02", "val": 274085523, "accn": "0001996810-26-000015", "fy": 2025, "fp": "FY", "form": "10-K", "filed": "2026-01-29", "frame": "CY2024Q1I"}, {"end": "2024-06-30", "val": 274701743, "accn": "0001996810-24-000067", "fy": 2024, "fp": "Q2", "form": "10-Q", "filed": "2024-07-24", "frame": "CY2024Q2I"}, {"end": "2024-09-30", "val": 275627753, "accn": "0001996810-24-000083", "fy": 2024, "fp": "Q3", "form": "10-Q", "filed": "2024-10-23", "frame": "CY2024Q3I"}, {"end": "2024-12-31", "val": 275880314, "accn": "0001996810-25-000011", "fy": 2024, "fp": "FY", "form": "10-K", "filed": "2025-02-06"}, {"end": "2024-12-31", "val": 275880314, "accn": "0001996810-25-000073", "fy": 2025, "fp": "Q1", "form": "10-Q", "filed": "2025-04-23"}, {"end": "2024-12-31", "val": 275880314, "accn": "0001996810-25-000133", "fy": 2025, "fp": "Q2", "form": "10-Q", "filed": "2025-07-23"}, {"end": "2024-12-31", "val": 275880314, "accn": "0001996810-25-000160", "fy": 2025, "fp": "Q3", "form": "10-Q", "filed": "2025-10-22"}, {"end": "2024-12-31", "val": 275880314, "accn": "0001996810-26-000015", "fy": 2025, "fp": "FY", "form": "10-K", "filed": "2026-01-29", "frame": "CY2024Q4I"}, {"end": "2025-03-31", "val": 272934744, "accn": "0001996810-25-000073", "fy": 2025, "fp": "Q1", "form": "10-Q", "filed": "2025-04-23", "frame": "CY2025Q1I"}, {"end": "2025-06-30", "val": 272223940, "accn": "0001996810-25-000133", "fy": 2025, "fp": "Q2", "form": "10-Q", "filed": "2025-07-23", "frame": "CY2025Q2I"}, {"end": "2025-09-30", "val": 271320459, "accn": "0001996810-25-000160", "fy": 2025, "fp": "Q3", "form": "10-Q", "filed": "2025-10-22", "frame": "CY2025Q3I"}, {"end": "2025-12-31", "val": 269529464, "accn": "0001996810-26-000015", "fy": 2025, "fp": "FY", "form": "10-K", "filed": "2026-01-29"}, {"end": "2025-12-31", "val": 269529464, "accn": "0001996810-26-000064", "fy": 2026, "fp": "Q1", "form": "10-Q", "filed": "2026-04-22", "frame": "CY2025Q4I"}, {"end": "2026-03-31", "val": 268719995, "accn": "0001996810-26-000064", "fy": 2026, "fp": "Q1", "form": "10-Q", "filed": "2026-04-22", "frame": "CY2026Q1I"}]}}}}}